Workbook

Sheet Assumptions
B2: Floating Offshore Wind Farm — Cost Model
B3: Dynamic line-item cost breakdown, rolling up to full wind-farm level. Real 2024 prices (£).
B5: Site definition
B6: Wind farm rating | C6: 1000 | D6: MW | E6: Total installed capacity — drives every full-farm total
B7: Turbine rating | C7: 15 | D7: MW
B8: Number of turbines | C8: =ROUND(C6/C7,0) | E8: =farm rating / turbine rating
B9: Water depth at site | C9: 100 | D9: m
B10: Annual mean wind speed at 100 m | C10: 10 | D10: m/s
B11: Offshore substation to shore | C11: 75 | D11: km
B12: Shore to onshore substation | C12: 10 | D12: km
B14: Programme
B15: Year of FID | C15: 2028 | E15: Discounting base year (t = 0)
B16: First operation date | C16: 2030
B17: Construction period | C17: 2 | D17: years | E17: CAPEX spread across the years before first operation
B18: Operational life | C18: 30 | D18: years | E18: Assumption — used for OPEX lifetime and LCOE
B20: Financial & energy
B21: Discount rate (WACC) | C21: 0.08 | E21: Real, pre-tax; used for LCOE discounting
B22: Gross capacity factor | C22: 0.55 | E22: Before availability & electrical losses
B23: Availability | C23: 0.95 | E23: Technical availability of the wind farm
B24: Electrical / transmission losses | C24: 0.03 | E24: Array + export + substation losses
B25: Net load factor | C25: =C22*C23*(1-C24) | E25: =gross CF × availability × (1 − losses)
B26: Net annual energy (AEP) | C26: =C6*8760*C25 | D26: MWh/yr | E26: =rating × 8,760 h × net load factor
B28: Cells shaded orange are inputs — change them and the whole model recalculates. All other figures are formulas.

Sheet Cost Breakdown
B2: Cost Breakdown Structure
B3: Line items roll up to assemblies and full wind-farm level. Use the +/− outline buttons on the left to collapse each assembly.
B5: Cost item | C5: Unit | D5: Rate | E5: Wind farm total | F5: Stated (source) | G5: Variance
B6: CAPEX — Capital expenditure (one-off) | C6: £/MW
B7: Development and project management | C7: £/MW | D7: =SUM(D8,D11,D15,D19,D23,D24) | E7: =D7*Assumptions!$C$6 | F7: 155000 | G7: =D7-F7
B8: Development and consenting services | C8: £/MW | D8: =SUM(D9,D10) | E8: =D8*Assumptions!$C$6 | F8: 72000 | G8: =D8-F8
B9: Environmental impact assessments | C9: £/MW | D9: 11000 | E9: =D9*Assumptions!$C$6 | F9: 11000 | G9: =D9-F9
B10: Development activities and other consenting services | C10: £/MW | D10: 62000 | E10: =D10*Assumptions!$C$6 | F10: 62000 | G10: =D10-F10
B11: Environmental surveys | C11: £/MW | D11: =SUM(D12,D13,D14) | E11: =D11*Assumptions!$C$6 | F11: 9000 | G11: =D11-F11
B12: Animal surveys (benthic, fish, shellfish, mammals and birds) | C12: £/MW | D12: 7000 | E12: =D12*Assumptions!$C$6 | F12: 7000 | G12: =D12-F12
B13: Onshore environmental surveys | C13: £/MW | D13: 1000 | E13: =D13*Assumptions!$C$6 | F13: 1000 | G13: =D13-F13
B14: Human impact studies | C14: £/MW | D14: 1000 | E14: =D14*Assumptions!$C$6 | F14: 1000 | G14: =D14-F14
B15: Resource and metocean assessment | C15: £/MW | D15: =SUM(D16,D17,D18) | E15: =D15*Assumptions!$C$6 | F15: 7000 | G15: =D15-F15
B16: Structure | C16: £/MW | D16: 4000 | E16: =D16*Assumptions!$C$6 | F16: 4000 | G16: =D16-F16
B17: Sensors | C17: £/MW | D17: 3000 | E17: =D17*Assumptions!$C$6 | F17: 3000 | G17: =D17-F17
B18: Maintenance | C18: £/MW | D18: 1000 | E18: =D18*Assumptions!$C$6 | F18: 1000 | G18: =D18-F18
B19: Geological and hydrographical surveys | C19: £/MW | D19: =SUM(D20,D21,D22) | E19: =D19*Assumptions!$C$6 | F19: 9000 | G19: =D19-F19
B20: Geophysical surveys | C20: £/MW | D20: 3000 | E20: =D20*Assumptions!$C$6 | F20: 3000 | G20: =D20-F20
B21: Geotechnical surveys | C21: £/MW | D21: 5000 | E21: =D21*Assumptions!$C$6 | F21: 5000 | G21: =D21-F21
B22: Hydrographic surveys | C22: £/MW | D22: 2000 | E22: =D22*Assumptions!$C$6 | F22: 2000 | G22: =D22-F22
B23: Engineering and consultancy | C23: £/MW | D23: 9000 | E23: =D23*Assumptions!$C$6 | F23: 9000 | G23: =D23-F23
B24: Project management | C24: £/MW | D24: 48000 | E24: =D24*Assumptions!$C$6 | F24: 48000 | G24: =D24-F24
B25: Wind turbine | C25: £/MW | D25: =SUM(D26,D27,D28) | E25: =D25*Assumptions!$C$6 | F25: 1350000 | G25: =D25-F25
B26: Nacelle | C26: £/MW | D26: 834000 | E26: =D26*Assumptions!$C$6 | F26: 834000 | G26: =D26-F26
B27: Rotor | C27: £/MW | D27: 360000 | E27: =D27*Assumptions!$C$6 | F27: 360000 | G27: =D27-F27
B28: Tower | C28: £/MW | D28: 156000 | E28: =D28*Assumptions!$C$6 | F28: 156000 | G28: =D28-F28
B29: Balance of plant | C29: £/MW | D29: =SUM(D30,D31,D32,D37,D42,D48,D53) | E29: =D29*Assumptions!$C$6 | F29: 2418000 | G29: =D29-F29
B30: Dynamic array cable | C30: £/MW | D30: 115000 | E30: =D30*Assumptions!$C$6 | F30: 115000 | G30: =D30-F30
B31: Export cable | C31: £/MW | D31: 269000 | E31: =D31*Assumptions!$C$6 | F31: 269000 | G31: =D31-F31
B32: Cable accessories | C32: £/MW | D32: =SUM(D33,D34,D35,D36) | E32: =D32*Assumptions!$C$6 | F32: 80000 | G32: =D32-F32
B33: Interface | C33: £/MW | D33: 30000 | E33: =D33*Assumptions!$C$6 | F33: 30000 | G33: =D33-F33
B34: Cable protection | C34: £/MW | D34: 4000 | E34: =D34*Assumptions!$C$6 | F34: 4000 | G34: =D34-F34
B35: Buoyancy | C35: £/MW | D35: 2000 | E35: =D35*Assumptions!$C$6 | F35: 2000 | G35: =D35-F35
B36: Connectors and joints | C36: £/MW | D36: 43000 | E36: =D36*Assumptions!$C$6 | F36: 43000 | G36: =D36-F36
B37: Floating substructure | C37: £/MW | D37: =SUM(D38,D39,D40,D41) | E37: =D37*Assumptions!$C$6 | F37: 1313000 | G37: =D37-F37
B38: Structure | C38: £/MW | D38: 1103000 | E38: =D38*Assumptions!$C$6 | F38: 1103000 | G38: =D38-F38
B39: Secondary steel | C39: £/MW | D39: 53000 | E39: =D39*Assumptions!$C$6 | F39: 53000 | G39: =D39-F39
B40: Systems | C40: £/MW | D40: 92000 | E40: =D40*Assumptions!$C$6 | F40: 92000 | G40: =D40-F40
B41: Corrosion protection | C41: £/MW | D41: 65000 | E41: =D41*Assumptions!$C$6 | F41: 65000 | G41: =D41-F41
B42: Mooring systems | C42: £/MW | D42: =SUM(D43,D44,D45,D46,D47) | E42: =D42*Assumptions!$C$6 | F42: 316000 | G42: =D42-F42
B43: Anchor systems | C43: £/MW | D43: 35000 | E43: =D43*Assumptions!$C$6 | F43: 35000 | G43: =D43-F43
B44: Mooring lines and chains | C44: £/MW | D44: 174000 | E44: =D44*Assumptions!$C$6 | F44: 174000 | G44: =D44-F44
B45: Jewellery | C45: £/MW | D45: 98000 | E45: =D45*Assumptions!$C$6 | F45: 98000 | G45: =D45-F45
B46: Topside connection | C46: £/MW | D46: 6000 | E46: =D46*Assumptions!$C$6 | F46: 6000 | G46: =D46-F46
B47: Installation aids | C47: £/MW | D47: 3000 | E47: =D47*Assumptions!$C$6 | F47: 3000 | G47: =D47-F47
B48: Offshore substation | C48: £/MW | D48: =SUM(D49,D50,D51,D52) | E48: =D48*Assumptions!$C$6 | F48: 282000 | G48: =D48-F48
B49: HVAC electrical system | C49: £/MW | D49: 80000 | E49: =D49*Assumptions!$C$6 | F49: 80000 | G49: =D49-F49
B50: Auxiliary systems | C50: £/MW | D50: 13000 | E50: =D50*Assumptions!$C$6 | F50: 13000 | G50: =D50-F50
B51: Topside structure | C51: £/MW | D51: 123000 | E51: =D51*Assumptions!$C$6 | F51: 123000 | G51: =D51-F51
B52: Foundation | C52: £/MW | D52: 65000 | E52: =D52*Assumptions!$C$6 | F52: 65000 | G52: =D52-F52
B53: Onshore substation | C53: £/MW | D53: =SUM(D54,D55) | E53: =D53*Assumptions!$C$6 | F53: 44000 | G53: =D53-F53
B54: Electrical system | C54: £/MW | D54: 31000 | E54: =D54*Assumptions!$C$6 | F54: 31000 | G54: =D54-F54
B55: Buildings, access and security | C55: £/MW | D55: 13000 | E55: =D55*Assumptions!$C$6 | F55: 13000 | G55: =D55-F55
B56: Installation and commissioning | C56: £/MW | D56: =SUM(D57,D58,D59,D64,D65,D66,D67,D68,D69,D74) | E56: =D56*Assumptions!$C$6 | F56: 1376000 | G56: =D56-F56
B57: Inbound transport | C57: £/MW | D57: 154000 | E57: =D57*Assumptions!$C$6 | F57: 154000 | G57: =D57-F57
B58: Mooring and anchoring pre-installation | C58: £/MW | D58: 153000 | E58: =D58*Assumptions!$C$6 | F58: 153000 | G58: =D58-F58
B59: Floating substructure - turbine assembly | C59: £/MW | D59: =SUM(D60,D61,D62,D63) | E59: =D59*Assumptions!$C$6 | F59: 72000 | G59: =D59-F59
B60: Crane and lifting equipment | C60: £/MW | D60: 34000 | E60: =D60*Assumptions!$C$6 | F60: 34000 | G60: =D60-F60
B61: Technician services | C61: £/MW | D61: 11000 | E61: =D61*Assumptions!$C$6 | F61: 11000 | G61: =D61-F61
B62: Marshalling port | C62: £/MW | D62: 22000 | E62: =D62*Assumptions!$C$6 | F62: 22000 | G62: =D62-F62
B63: Other | C63: £/MW | D63: 5000 | E63: =D63*Assumptions!$C$6 | F63: 5000 | G63: =D63-F63
B64: Floating substructure - turbine installation | C64: £/MW | D64: 114000 | E64: =D64*Assumptions!$C$6 | F64: 114000 | G64: =D64-F64
B65: Offshore cable installation | C65: £/MW | D65: 171000 | E65: =D65*Assumptions!$C$6 | F65: 171000 | G65: =D65-F65
B66: Onshore export cable installation | C66: £/MW | D66: 8000 | E66: =D66*Assumptions!$C$6 | F66: 8000 | G66: =D66-F66
B67: Offshore substation installation | C67: £/MW | D67: 52000 | E67: =D67*Assumptions!$C$6 | F67: 52000 | G67: =D67-F67
B68: Onshore substation construction | C68: £/MW | D68: 29000 | E68: =D68*Assumptions!$C$6 | F68: 29000 | G68: =D68-F68
B69: Offshore logistics | C69: £/MW | D69: =SUM(D70,D71,D72,D73) | E69: =D69*Assumptions!$C$6 | F69: 13000 | G69: =D69-F69
B70: Sea-based support | C70: £/MW | D70: 6000 | E70: =D70*Assumptions!$C$6 | F70: 6000 | G70: =D70-F70
B71: Marine coordination | C71: £/MW | D71: 2000 | E71: =D71*Assumptions!$C$6 | F71: 2000 | G71: =D71-F71
B72: Weather forecasting and metocean data | C72: £/MW | D72: 1000 | E72: =D72*Assumptions!$C$6 | F72: 1000 | G72: =D72-F72
B73: Marine safety and rescue | C73: £/MW | D73: 4000 | E73: =D73*Assumptions!$C$6 | F73: 4000 | G73: =D73-F73
B74: Contingency and insurance | C74: £/MW | D74: 610000 | E74: =D74*Assumptions!$C$6 | F74: 610000 | G74: =D74-F74
B75: TOTAL CAPEX (build cost) | D75: =SUM(D7,D25,D29,D56) | E75: =D75*Assumptions!$C$6
B77: OPEX — Operating expenditure (annual) | C77: £/MW/yr
B78: Operation, maintenance and service | C78: £/MW/yr | D78: =SUM(D79,D80,D88) | E78: =D78*Assumptions!$C$6 | F78: 98000 | G78: =D78-F78
B79: Operations, maintenance and service port | C79: £/MW/yr | D79: 0 | E79: =D79*Assumptions!$C$6 | F79: 0 | G79: =D79-F79
B80: Operations | C80: £/MW/yr | D80: =SUM(D81,D82,D83,D84,D85,D86,D87) | E80: =D80*Assumptions!$C$6 | F80: 34000 | G80: =D80-F80
B81: Operations control centre | C81: £/MW/yr | D81: 1000 | E81: =D81*Assumptions!$C$6 | F81: 1000 | G81: =D81-F81
B82: Training | C82: £/MW/yr | D82: 3000 | E82: =D82*Assumptions!$C$6 | F82: 3000 | G82: =D82-F82
B83: Onshore logistics | C83: £/MW/yr | D83: 1000 | E83: =D83*Assumptions!$C$6 | F83: 1000 | G83: =D83-F83
B84: Technical resource (onshore and off) | C84: £/MW/yr | D84: 7000 | E84: =D84*Assumptions!$C$6 | F84: 7000 | G84: =D84-F84
B85: Admin and support staff (onshore) | C85: £/MW/yr | D85: 8000 | E85: =D85*Assumptions!$C$6 | F85: 8000 | G85: =D85-F85
B86: Insurance | C86: £/MW/yr | D86: 14000 | E86: =D86*Assumptions!$C$6 | F86: 14000 | G86: =D86-F86
B87: Offshore logistics | C87: £/MW/yr | D87: 7000 | E87: =D87*Assumptions!$C$6 | F87: 7000 | G87: =D87-F87
B88: Maintenance and service | C88: £/MW/yr | D88: =SUM(D89,D90,D91) | E88: =D88*Assumptions!$C$6 | F88: 57000 | G88: =D88-F88
B89: Turbine maintenance and service | C89: £/MW/yr | D89: 41000 | E89: =D89*Assumptions!$C$6 | F89: 41000 | G89: =D89-F89
B90: Balance of plant maintenance and service | C90: £/MW/yr | D90: 15000 | E90: =D90*Assumptions!$C$6 | F90: 15000 | G90: =D90-F90
B91: Statutory inspections | C91: £/MW/yr | D91: 1000 | E91: =D91*Assumptions!$C$6 | F91: 1000 | G91: =D91-F91
B92: TOTAL OPEX (per year) | D92: =SUM(D78) | E92: =D92*Assumptions!$C$6
B94: DECEX — Decommissioning (end of life) | C94: £/MW
B95: Decommissioning | C95: £/MW | D95: =SUM(D96,D97,D98,D99) | E95: =D95*Assumptions!$C$6 | F95: 450000 | G95: =D95-F95
B96: Floating hull - turbine decommissioning | C96: £/MW | D96: 148000 | E96: =D96*Assumptions!$C$6 | F96: 148000 | G96: =D96-F96
B97: Mooring and anchoring decommissioning | C97: £/MW | D97: 122000 | E97: =D97*Assumptions!$C$6 | F97: 122000 | G97: =D97-F97
B98: Cable decommissioning | C98: £/MW | D98: 137000 | E98: =D98*Assumptions!$C$6 | F98: 137000 | G98: =D98-F98
B99: Substation decommissioning | C99: £/MW | D99: 42000 | E99: =D99*Assumptions!$C$6 | F99: 42000 | G99: =D99-F99
B100: TOTAL DECEX (decommissioning) | D100: =SUM(D95) | E100: =D100*Assumptions!$C$6
B102: LIFETIME COST (CAPEX + OPEX×life + DECEX) | C102: £/MW | D102: =D75+D92*Assumptions!$C$18+D100 | E102: =D102*Assumptions!$C$6
B104: Notes: 'Rate' leaf cells are inputs; every assembly/category is =SUM(children), so editing a line item rolls up automatically. 'Wind farm total' = Rate × farm rating (£/yr for OPEX rows). 'Stated (source)' is the published rounded figure; 'Variance' is the small rounding gap between the computed roll-up and the published total.

Sheet Lifetime Summary
B2: Lifetime Cost Summary
B3: Contribution of each major cost element to whole-life cost of the wind farm.
B5: Cost element | C5: Lifetime cost (£) | D5: Per MW (£/MW) | E5: % of total
B6: Development and project management | C6: ='Cost Breakdown'!E7 | D6: ='Cost Breakdown'!D7 | E6: =C6/$C$12
B7: Wind turbine | C7: ='Cost Breakdown'!E25 | D7: ='Cost Breakdown'!D25 | E7: =C7/$C$12
B8: Balance of plant | C8: ='Cost Breakdown'!E29 | D8: ='Cost Breakdown'!D29 | E8: =C8/$C$12
B9: Installation and commissioning | C9: ='Cost Breakdown'!E56 | D9: ='Cost Breakdown'!D56 | E9: =C9/$C$12
B10: Operation, maintenance and service | C10: ='Cost Breakdown'!E78*Assumptions!$C$18 | D10: ='Cost Breakdown'!D78*Assumptions!$C$18 | E10: =C10/$C$12
B11: Decommissioning | C11: ='Cost Breakdown'!E95 | D11: ='Cost Breakdown'!D95 | E11: =C11/$C$12
B12: TOTAL LIFETIME COST | C12: =SUM(C6:C11) | D12: =SUM(D6:D11) | E12: =SUM(E6:E11)

Sheet LCOE
B2: Levelised Cost of Energy (LCOE)
B3: Discounted cash-flow model. LCOE = Σ(discounted cost) / Σ(discounted energy), discounted to the year of FID.
B5: LCOE | C5: =J54/K54
B6: £ per MWh, real 2024, discounted to FID
B8: Year | C8: t | D8: CAPEX (£) | E8: OPEX (£) | F8: DECEX (£) | G8: Total cost (£) | H8: Energy (MWh) | I8: Discount factor | J8: Disc. cost (£) | K8: Disc. energy (MWh)
B9: =Assumptions!$C$15+0 | C9: 0 | D9: =IF(B9<Assumptions!$C$16,'Cost Breakdown'!$E$75/Assumptions!$C$17,0) | E9: =IF(AND(B9>=Assumptions!$C$16,B9<Assumptions!$C$16+Assumptions!$C$18),'Cost Breakdown'!$E$92,0) | F9: =IF(B9=Assumptions!$C$16+Assumptions!$C$18,'Cost Breakdown'!$E$100,0) | G9: =D9+E9+F9 | H9: =IF(AND(B9>=Assumptions!$C$16,B9<Assumptions!$C$16+Assumptions!$C$18),Assumptions!$C$26,0) | I9: =1/(1+Assumptions!$C$21)^C9 | J9: =G9*I9 | K9: =H9*I9
B10: =Assumptions!$C$15+1 | C10: 1 | D10: =IF(B10<Assumptions!$C$16,'Cost Breakdown'!$E$75/Assumptions!$C$17,0) | E10: =IF(AND(B10>=Assumptions!$C$16,B10<Assumptions!$C$16+Assumptions!$C$18),'Cost Breakdown'!$E$92,0) | F10: =IF(B10=Assumptions!$C$16+Assumptions!$C$18,'Cost Breakdown'!$E$100,0) | G10: =D10+E10+F10 | H10: =IF(AND(B10>=Assumptions!$C$16,B10<Assumptions!$C$16+Assumptions!$C$18),Assumptions!$C$26,0) | I10: =1/(1+Assumptions!$C$21)^C10 | J10: =G10*I10 | K10: =H10*I10
B11: =Assumptions!$C$15+2 | C11: 2 | D11: =IF(B11<Assumptions!$C$16,'Cost Breakdown'!$E$75/Assumptions!$C$17,0) | E11: =IF(AND(B11>=Assumptions!$C$16,B11<Assumptions!$C$16+Assumptions!$C$18),'Cost Breakdown'!$E$92,0) | F11: =IF(B11=Assumptions!$C$16+Assumptions!$C$18,'Cost Breakdown'!$E$100,0) | G11: =D11+E11+F11 | H11: =IF(AND(B11>=Assumptions!$C$16,B11<Assumptions!$C$16+Assumptions!$C$18),Assumptions!$C$26,0) | I11: =1/(1+Assumptions!$C$21)^C11 | J11: =G11*I11 | K11: =H11*I11
B12: =Assumptions!$C$15+3 | C12: 3 | D12: =IF(B12<Assumptions!$C$16,'Cost Breakdown'!$E$75/Assumptions!$C$17,0) | E12: =IF(AND(B12>=Assumptions!$C$16,B12<Assumptions!$C$16+Assumptions!$C$18),'Cost Breakdown'!$E$92,0) | F12: =IF(B12=Assumptions!$C$16+Assumptions!$C$18,'Cost Breakdown'!$E$100,0) | G12: =D12+E12+F12 | H12: =IF(AND(B12>=Assumptions!$C$16,B12<Assumptions!$C$16+Assumptions!$C$18),Assumptions!$C$26,0) | I12: =1/(1+Assumptions!$C$21)^C12 | J12: =G12*I12 | K12: =H12*I12
B13: =Assumptions!$C$15+4 | C13: 4 | D13: =IF(B13<Assumptions!$C$16,'Cost Breakdown'!$E$75/Assumptions!$C$17,0) | E13: =IF(AND(B13>=Assumptions!$C$16,B13<Assumptions!$C$16+Assumptions!$C$18),'Cost Breakdown'!$E$92,0) | F13: =IF(B13=Assumptions!$C$16+Assumptions!$C$18,'Cost Breakdown'!$E$100,0) | G13: =D13+E13+F13 | H13: =IF(AND(B13>=Assumptions!$C$16,B13<Assumptions!$C$16+Assumptions!$C$18),Assumptions!$C$26,0) | I13: =1/(1+Assumptions!$C$21)^C13 | J13: =G13*I13 | K13: =H13*I13
B14: =Assumptions!$C$15+5 | C14: 5 | D14: =IF(B14<Assumptions!$C$16,'Cost Breakdown'!$E$75/Assumptions!$C$17,0) | E14: =IF(AND(B14>=Assumptions!$C$16,B14<Assumptions!$C$16+Assumptions!$C$18),'Cost Breakdown'!$E$92,0) | F14: =IF(B14=Assumptions!$C$16+Assumptions!$C$18,'Cost Breakdown'!$E$100,0) | G14: =D14+E14+F14 | H14: =IF(AND(B14>=Assumptions!$C$16,B14<Assumptions!$C$16+Assumptions!$C$18),Assumptions!$C$26,0) | I14: =1/(1+Assumptions!$C$21)^C14 | J14: =G14*I14 | K14: =H14*I14
B15: =Assumptions!$C$15+6 | C15: 6 | D15: =IF(B15<Assumptions!$C$16,'Cost Breakdown'!$E$75/Assumptions!$C$17,0) | E15: =IF(AND(B15>=Assumptions!$C$16,B15<Assumptions!$C$16+Assumptions!$C$18),'Cost Breakdown'!$E$92,0) | F15: =IF(B15=Assumptions!$C$16+Assumptions!$C$18,'Cost Breakdown'!$E$100,0) | G15: =D15+E15+F15 | H15: =IF(AND(B15>=Assumptions!$C$16,B15<Assumptions!$C$16+Assumptions!$C$18),Assumptions!$C$26,0) | I15: =1/(1+Assumptions!$C$21)^C15 | J15: =G15*I15 | K15: =H15*I15
B16: =Assumptions!$C$15+7 | C16: 7 | D16: =IF(B16<Assumptions!$C$16,'Cost Breakdown'!$E$75/Assumptions!$C$17,0) | E16: =IF(AND(B16>=Assumptions!$C$16,B16<Assumptions!$C$16+Assumptions!$C$18),'Cost Breakdown'!$E$92,0) | F16: =IF(B16=Assumptions!$C$16+Assumptions!$C$18,'Cost Breakdown'!$E$100,0) | G16: =D16+E16+F16 | H16: =IF(AND(B16>=Assumptions!$C$16,B16<Assumptions!$C$16+Assumptions!$C$18),Assumptions!$C$26,0) | I16: =1/(1+Assumptions!$C$21)^C16 | J16: =G16*I16 | K16: =H16*I16
B17: =Assumptions!$C$15+8 | C17: 8 | D17: =IF(B17<Assumptions!$C$16,'Cost Breakdown'!$E$75/Assumptions!$C$17,0) | E17: =IF(AND(B17>=Assumptions!$C$16,B17<Assumptions!$C$16+Assumptions!$C$18),'Cost Breakdown'!$E$92,0) | F17: =IF(B17=Assumptions!$C$16+Assumptions!$C$18,'Cost Breakdown'!$E$100,0) | G17: =D17+E17+F17 | H17: =IF(AND(B17>=Assumptions!$C$16,B17<Assumptions!$C$16+Assumptions!$C$18),Assumptions!$C$26,0) | I17: =1/(1+Assumptions!$C$21)^C17 | J17: =G17*I17 | K17: =H17*I17
B18: =Assumptions!$C$15+9 | C18: 9 | D18: =IF(B18<Assumptions!$C$16,'Cost Breakdown'!$E$75/Assumptions!$C$17,0) | E18: =IF(AND(B18>=Assumptions!$C$16,B18<Assumptions!$C$16+Assumptions!$C$18),'Cost Breakdown'!$E$92,0) | F18: =IF(B18=Assumptions!$C$16+Assumptions!$C$18,'Cost Breakdown'!$E$100,0) | G18: =D18+E18+F18 | H18: =IF(AND(B18>=Assumptions!$C$16,B18<Assumptions!$C$16+Assumptions!$C$18),Assumptions!$C$26,0) | I18: =1/(1+Assumptions!$C$21)^C18 | J18: =G18*I18 | K18: =H18*I18
B19: =Assumptions!$C$15+10 | C19: 10 | D19: =IF(B19<Assumptions!$C$16,'Cost Breakdown'!$E$75/Assumptions!$C$17,0) | E19: =IF(AND(B19>=Assumptions!$C$16,B19<Assumptions!$C$16+Assumptions!$C$18),'Cost Breakdown'!$E$92,0) | F19: =IF(B19=Assumptions!$C$16+Assumptions!$C$18,'Cost Breakdown'!$E$100,0) | G19: =D19+E19+F19 | H19: =IF(AND(B19>=Assumptions!$C$16,B19<Assumptions!$C$16+Assumptions!$C$18),Assumptions!$C$26,0) | I19: =1/(1+Assumptions!$C$21)^C19 | J19: =G19*I19 | K19: =H19*I19
B20: =Assumptions!$C$15+11 | C20: 11 | D20: =IF(B20<Assumptions!$C$16,'Cost Breakdown'!$E$75/Assumptions!$C$17,0) | E20: =IF(AND(B20>=Assumptions!$C$16,B20<Assumptions!$C$16+Assumptions!$C$18),'Cost Breakdown'!$E$92,0) | F20: =IF(B20=Assumptions!$C$16+Assumptions!$C$18,'Cost Breakdown'!$E$100,0) | G20: =D20+E20+F20 | H20: =IF(AND(B20>=Assumptions!$C$16,B20<Assumptions!$C$16+Assumptions!$C$18),Assumptions!$C$26,0) | I20: =1/(1+Assumptions!$C$21)^C20 | J20: =G20*I20 | K20: =H20*I20
B21: =Assumptions!$C$15+12 | C21: 12 | D21: =IF(B21<Assumptions!$C$16,'Cost Breakdown'!$E$75/Assumptions!$C$17,0) | E21: =IF(AND(B21>=Assumptions!$C$16,B21<Assumptions!$C$16+Assumptions!$C$18),'Cost Breakdown'!$E$92,0) | F21: =IF(B21=Assumptions!$C$16+Assumptions!$C$18,'Cost Breakdown'!$E$100,0) | G21: =D21+E21+F21 | H21: =IF(AND(B21>=Assumptions!$C$16,B21<Assumptions!$C$16+Assumptions!$C$18),Assumptions!$C$26,0) | I21: =1/(1+Assumptions!$C$21)^C21 | J21: =G21*I21 | K21: =H21*I21
B22: =Assumptions!$C$15+13 | C22: 13 | D22: =IF(B22<Assumptions!$C$16,'Cost Breakdown'!$E$75/Assumptions!$C$17,0) | E22: =IF(AND(B22>=Assumptions!$C$16,B22<Assumptions!$C$16+Assumptions!$C$18),'Cost Breakdown'!$E$92,0) | F22: =IF(B22=Assumptions!$C$16+Assumptions!$C$18,'Cost Breakdown'!$E$100,0) | G22: =D22+E22+F22 | H22: =IF(AND(B22>=Assumptions!$C$16,B22<Assumptions!$C$16+Assumptions!$C$18),Assumptions!$C$26,0) | I22: =1/(1+Assumptions!$C$21)^C22 | J22: =G22*I22 | K22: =H22*I22
B23: =Assumptions!$C$15+14 | C23: 14 | D23: =IF(B23<Assumptions!$C$16,'Cost Breakdown'!$E$75/Assumptions!$C$17,0) | E23: =IF(AND(B23>=Assumptions!$C$16,B23<Assumptions!$C$16+Assumptions!$C$18),'Cost Breakdown'!$E$92,0) | F23: =IF(B23=Assumptions!$C$16+Assumptions!$C$18,'Cost Breakdown'!$E$100,0) | G23: =D23+E23+F23 | H23: =IF(AND(B23>=Assumptions!$C$16,B23<Assumptions!$C$16+Assumptions!$C$18),Assumptions!$C$26,0) | I23: =1/(1+Assumptions!$C$21)^C23 | J23: =G23*I23 | K23: =H23*I23
B24: =Assumptions!$C$15+15 | C24: 15 | D24: =IF(B24<Assumptions!$C$16,'Cost Breakdown'!$E$75/Assumptions!$C$17,0) | E24: =IF(AND(B24>=Assumptions!$C$16,B24<Assumptions!$C$16+Assumptions!$C$18),'Cost Breakdown'!$E$92,0) | F24: =IF(B24=Assumptions!$C$16+Assumptions!$C$18,'Cost Breakdown'!$E$100,0) | G24: =D24+E24+F24 | H24: =IF(AND(B24>=Assumptions!$C$16,B24<Assumptions!$C$16+Assumptions!$C$18),Assumptions!$C$26,0) | I24: =1/(1+Assumptions!$C$21)^C24 | J24: =G24*I24 | K24: =H24*I24
B25: =Assumptions!$C$15+16 | C25: 16 | D25: =IF(B25<Assumptions!$C$16,'Cost Breakdown'!$E$75/Assumptions!$C$17,0) | E25: =IF(AND(B25>=Assumptions!$C$16,B25<Assumptions!$C$16+Assumptions!$C$18),'Cost Breakdown'!$E$92,0) | F25: =IF(B25=Assumptions!$C$16+Assumptions!$C$18,'Cost Breakdown'!$E$100,0) | G25: =D25+E25+F25 | H25: =IF(AND(B25>=Assumptions!$C$16,B25<Assumptions!$C$16+Assumptions!$C$18),Assumptions!$C$26,0) | I25: =1/(1+Assumptions!$C$21)^C25 | J25: =G25*I25 | K25: =H25*I25
B26: =Assumptions!$C$15+17 | C26: 17 | D26: =IF(B26<Assumptions!$C$16,'Cost Breakdown'!$E$75/Assumptions!$C$17,0) | E26: =IF(AND(B26>=Assumptions!$C$16,B26<Assumptions!$C$16+Assumptions!$C$18),'Cost Breakdown'!$E$92,0) | F26: =IF(B26=Assumptions!$C$16+Assumptions!$C$18,'Cost Breakdown'!$E$100,0) | G26: =D26+E26+F26 | H26: =IF(AND(B26>=Assumptions!$C$16,B26<Assumptions!$C$16+Assumptions!$C$18),Assumptions!$C$26,0) | I26: =1/(1+Assumptions!$C$21)^C26 | J26: =G26*I26 | K26: =H26*I26
B27: =Assumptions!$C$15+18 | C27: 18 | D27: =IF(B27<Assumptions!$C$16,'Cost Breakdown'!$E$75/Assumptions!$C$17,0) | E27: =IF(AND(B27>=Assumptions!$C$16,B27<Assumptions!$C$16+Assumptions!$C$18),'Cost Breakdown'!$E$92,0) | F27: =IF(B27=Assumptions!$C$16+Assumptions!$C$18,'Cost Breakdown'!$E$100,0) | G27: =D27+E27+F27 | H27: =IF(AND(B27>=Assumptions!$C$16,B27<Assumptions!$C$16+Assumptions!$C$18),Assumptions!$C$26,0) | I27: =1/(1+Assumptions!$C$21)^C27 | J27: =G27*I27 | K27: =H27*I27
B28: =Assumptions!$C$15+19 | C28: 19 | D28: =IF(B28<Assumptions!$C$16,'Cost Breakdown'!$E$75/Assumptions!$C$17,0) | E28: =IF(AND(B28>=Assumptions!$C$16,B28<Assumptions!$C$16+Assumptions!$C$18),'Cost Breakdown'!$E$92,0) | F28: =IF(B28=Assumptions!$C$16+Assumptions!$C$18,'Cost Breakdown'!$E$100,0) | G28: =D28+E28+F28 | H28: =IF(AND(B28>=Assumptions!$C$16,B28<Assumptions!$C$16+Assumptions!$C$18),Assumptions!$C$26,0) | I28: =1/(1+Assumptions!$C$21)^C28 | J28: =G28*I28 | K28: =H28*I28
B29: =Assumptions!$C$15+20 | C29: 20 | D29: =IF(B29<Assumptions!$C$16,'Cost Breakdown'!$E$75/Assumptions!$C$17,0) | E29: =IF(AND(B29>=Assumptions!$C$16,B29<Assumptions!$C$16+Assumptions!$C$18),'Cost Breakdown'!$E$92,0) | F29: =IF(B29=Assumptions!$C$16+Assumptions!$C$18,'Cost Breakdown'!$E$100,0) | G29: =D29+E29+F29 | H29: =IF(AND(B29>=Assumptions!$C$16,B29<Assumptions!$C$16+Assumptions!$C$18),Assumptions!$C$26,0) | I29: =1/(1+Assumptions!$C$21)^C29 | J29: =G29*I29 | K29: =H29*I29
B30: =Assumptions!$C$15+21 | C30: 21 | D30: =IF(B30<Assumptions!$C$16,'Cost Breakdown'!$E$75/Assumptions!$C$17,0) | E30: =IF(AND(B30>=Assumptions!$C$16,B30<Assumptions!$C$16+Assumptions!$C$18),'Cost Breakdown'!$E$92,0) | F30: =IF(B30=Assumptions!$C$16+Assumptions!$C$18,'Cost Breakdown'!$E$100,0) | G30: =D30+E30+F30 | H30: =IF(AND(B30>=Assumptions!$C$16,B30<Assumptions!$C$16+Assumptions!$C$18),Assumptions!$C$26,0) | I30: =1/(1+Assumptions!$C$21)^C30 | J30: =G30*I30 | K30: =H30*I30
B31: =Assumptions!$C$15+22 | C31: 22 | D31: =IF(B31<Assumptions!$C$16,'Cost Breakdown'!$E$75/Assumptions!$C$17,0) | E31: =IF(AND(B31>=Assumptions!$C$16,B31<Assumptions!$C$16+Assumptions!$C$18),'Cost Breakdown'!$E$92,0) | F31: =IF(B31=Assumptions!$C$16+Assumptions!$C$18,'Cost Breakdown'!$E$100,0) | G31: =D31+E31+F31 | H31: =IF(AND(B31>=Assumptions!$C$16,B31<Assumptions!$C$16+Assumptions!$C$18),Assumptions!$C$26,0) | I31: =1/(1+Assumptions!$C$21)^C31 | J31: =G31*I31 | K31: =H31*I31
B32: =Assumptions!$C$15+23 | C32: 23 | D32: =IF(B32<Assumptions!$C$16,'Cost Breakdown'!$E$75/Assumptions!$C$17,0) | E32: =IF(AND(B32>=Assumptions!$C$16,B32<Assumptions!$C$16+Assumptions!$C$18),'Cost Breakdown'!$E$92,0) | F32: =IF(B32=Assumptions!$C$16+Assumptions!$C$18,'Cost Breakdown'!$E$100,0) | G32: =D32+E32+F32 | H32: =IF(AND(B32>=Assumptions!$C$16,B32<Assumptions!$C$16+Assumptions!$C$18),Assumptions!$C$26,0) | I32: =1/(1+Assumptions!$C$21)^C32 | J32: =G32*I32 | K32: =H32*I32
B33: =Assumptions!$C$15+24 | C33: 24 | D33: =IF(B33<Assumptions!$C$16,'Cost Breakdown'!$E$75/Assumptions!$C$17,0) | E33: =IF(AND(B33>=Assumptions!$C$16,B33<Assumptions!$C$16+Assumptions!$C$18),'Cost Breakdown'!$E$92,0) | F33: =IF(B33=Assumptions!$C$16+Assumptions!$C$18,'Cost Breakdown'!$E$100,0) | G33: =D33+E33+F33 | H33: =IF(AND(B33>=Assumptions!$C$16,B33<Assumptions!$C$16+Assumptions!$C$18),Assumptions!$C$26,0) | I33: =1/(1+Assumptions!$C$21)^C33 | J33: =G33*I33 | K33: =H33*I33
B34: =Assumptions!$C$15+25 | C34: 25 | D34: =IF(B34<Assumptions!$C$16,'Cost Breakdown'!$E$75/Assumptions!$C$17,0) | E34: =IF(AND(B34>=Assumptions!$C$16,B34<Assumptions!$C$16+Assumptions!$C$18),'Cost Breakdown'!$E$92,0) | F34: =IF(B34=Assumptions!$C$16+Assumptions!$C$18,'Cost Breakdown'!$E$100,0) | G34: =D34+E34+F34 | H34: =IF(AND(B34>=Assumptions!$C$16,B34<Assumptions!$C$16+Assumptions!$C$18),Assumptions!$C$26,0) | I34: =1/(1+Assumptions!$C$21)^C34 | J34: =G34*I34 | K34: =H34*I34
B35: =Assumptions!$C$15+26 | C35: 26 | D35: =IF(B35<Assumptions!$C$16,'Cost Breakdown'!$E$75/Assumptions!$C$17,0) | E35: =IF(AND(B35>=Assumptions!$C$16,B35<Assumptions!$C$16+Assumptions!$C$18),'Cost Breakdown'!$E$92,0) | F35: =IF(B35=Assumptions!$C$16+Assumptions!$C$18,'Cost Breakdown'!$E$100,0) | G35: =D35+E35+F35 | H35: =IF(AND(B35>=Assumptions!$C$16,B35<Assumptions!$C$16+Assumptions!$C$18),Assumptions!$C$26,0) | I35: =1/(1+Assumptions!$C$21)^C35 | J35: =G35*I35 | K35: =H35*I35
B36: =Assumptions!$C$15+27 | C36: 27 | D36: =IF(B36<Assumptions!$C$16,'Cost Breakdown'!$E$75/Assumptions!$C$17,0) | E36: =IF(AND(B36>=Assumptions!$C$16,B36<Assumptions!$C$16+Assumptions!$C$18),'Cost Breakdown'!$E$92,0) | F36: =IF(B36=Assumptions!$C$16+Assumptions!$C$18,'Cost Breakdown'!$E$100,0) | G36: =D36+E36+F36 | H36: =IF(AND(B36>=Assumptions!$C$16,B36<Assumptions!$C$16+Assumptions!$C$18),Assumptions!$C$26,0) | I36: =1/(1+Assumptions!$C$21)^C36 | J36: =G36*I36 | K36: =H36*I36
B37: =Assumptions!$C$15+28 | C37: 28 | D37: =IF(B37<Assumptions!$C$16,'Cost Breakdown'!$E$75/Assumptions!$C$17,0) | E37: =IF(AND(B37>=Assumptions!$C$16,B37<Assumptions!$C$16+Assumptions!$C$18),'Cost Breakdown'!$E$92,0) | F37: =IF(B37=Assumptions!$C$16+Assumptions!$C$18,'Cost Breakdown'!$E$100,0) | G37: =D37+E37+F37 | H37: =IF(AND(B37>=Assumptions!$C$16,B37<Assumptions!$C$16+Assumptions!$C$18),Assumptions!$C$26,0) | I37: =1/(1+Assumptions!$C$21)^C37 | J37: =G37*I37 | K37: =H37*I37
B38: =Assumptions!$C$15+29 | C38: 29 | D38: =IF(B38<Assumptions!$C$16,'Cost Breakdown'!$E$75/Assumptions!$C$17,0) | E38: =IF(AND(B38>=Assumptions!$C$16,B38<Assumptions!$C$16+Assumptions!$C$18),'Cost Breakdown'!$E$92,0) | F38: =IF(B38=Assumptions!$C$16+Assumptions!$C$18,'Cost Breakdown'!$E$100,0) | G38: =D38+E38+F38 | H38: =IF(AND(B38>=Assumptions!$C$16,B38<Assumptions!$C$16+Assumptions!$C$18),Assumptions!$C$26,0) | I38: =1/(1+Assumptions!$C$21)^C38 | J38: =G38*I38 | K38: =H38*I38
B39: =Assumptions!$C$15+30 | C39: 30 | D39: =IF(B39<Assumptions!$C$16,'Cost Breakdown'!$E$75/Assumptions!$C$17,0) | E39: =IF(AND(B39>=Assumptions!$C$16,B39<Assumptions!$C$16+Assumptions!$C$18),'Cost Breakdown'!$E$92,0) | F39: =IF(B39=Assumptions!$C$16+Assumptions!$C$18,'Cost Breakdown'!$E$100,0) | G39: =D39+E39+F39 | H39: =IF(AND(B39>=Assumptions!$C$16,B39<Assumptions!$C$16+Assumptions!$C$18),Assumptions!$C$26,0) | I39: =1/(1+Assumptions!$C$21)^C39 | J39: =G39*I39 | K39: =H39*I39
B40: =Assumptions!$C$15+31 | C40: 31 | D40: =IF(B40<Assumptions!$C$16,'Cost Breakdown'!$E$75/Assumptions!$C$17,0) | E40: =IF(AND(B40>=Assumptions!$C$16,B40<Assumptions!$C$16+Assumptions!$C$18),'Cost Breakdown'!$E$92,0) | F40: =IF(B40=Assumptions!$C$16+Assumptions!$C$18,'Cost Breakdown'!$E$100,0) | G40: =D40+E40+F40 | H40: =IF(AND(B40>=Assumptions!$C$16,B40<Assumptions!$C$16+Assumptions!$C$18),Assumptions!$C$26,0) | I40: =1/(1+Assumptions!$C$21)^C40 | J40: =G40*I40 | K40: =H40*I40
B41: =Assumptions!$C$15+32 | C41: 32 | D41: =IF(B41<Assumptions!$C$16,'Cost Breakdown'!$E$75/Assumptions!$C$17,0) | E41: =IF(AND(B41>=Assumptions!$C$16,B41<Assumptions!$C$16+Assumptions!$C$18),'Cost Breakdown'!$E$92,0) | F41: =IF(B41=Assumptions!$C$16+Assumptions!$C$18,'Cost Breakdown'!$E$100,0) | G41: =D41+E41+F41 | H41: =IF(AND(B41>=Assumptions!$C$16,B41<Assumptions!$C$16+Assumptions!$C$18),Assumptions!$C$26,0) | I41: =1/(1+Assumptions!$C$21)^C41 | J41: =G41*I41 | K41: =H41*I41
B42: =Assumptions!$C$15+33 | C42: 33 | D42: =IF(B42<Assumptions!$C$16,'Cost Breakdown'!$E$75/Assumptions!$C$17,0) | E42: =IF(AND(B42>=Assumptions!$C$16,B42<Assumptions!$C$16+Assumptions!$C$18),'Cost Breakdown'!$E$92,0) | F42: =IF(B42=Assumptions!$C$16+Assumptions!$C$18,'Cost Breakdown'!$E$100,0) | G42: =D42+E42+F42 | H42: =IF(AND(B42>=Assumptions!$C$16,B42<Assumptions!$C$16+Assumptions!$C$18),Assumptions!$C$26,0) | I42: =1/(1+Assumptions!$C$21)^C42 | J42: =G42*I42 | K42: =H42*I42
B43: =Assumptions!$C$15+34 | C43: 34 | D43: =IF(B43<Assumptions!$C$16,'Cost Breakdown'!$E$75/Assumptions!$C$17,0) | E43: =IF(AND(B43>=Assumptions!$C$16,B43<Assumptions!$C$16+Assumptions!$C$18),'Cost Breakdown'!$E$92,0) | F43: =IF(B43=Assumptions!$C$16+Assumptions!$C$18,'Cost Breakdown'!$E$100,0) | G43: =D43+E43+F43 | H43: =IF(AND(B43>=Assumptions!$C$16,B43<Assumptions!$C$16+Assumptions!$C$18),Assumptions!$C$26,0) | I43: =1/(1+Assumptions!$C$21)^C43 | J43: =G43*I43 | K43: =H43*I43
B44: =Assumptions!$C$15+35 | C44: 35 | D44: =IF(B44<Assumptions!$C$16,'Cost Breakdown'!$E$75/Assumptions!$C$17,0) | E44: =IF(AND(B44>=Assumptions!$C$16,B44<Assumptions!$C$16+Assumptions!$C$18),'Cost Breakdown'!$E$92,0) | F44: =IF(B44=Assumptions!$C$16+Assumptions!$C$18,'Cost Breakdown'!$E$100,0) | G44: =D44+E44+F44 | H44: =IF(AND(B44>=Assumptions!$C$16,B44<Assumptions!$C$16+Assumptions!$C$18),Assumptions!$C$26,0) | I44: =1/(1+Assumptions!$C$21)^C44 | J44: =G44*I44 | K44: =H44*I44
B45: =Assumptions!$C$15+36 | C45: 36 | D45: =IF(B45<Assumptions!$C$16,'Cost Breakdown'!$E$75/Assumptions!$C$17,0) | E45: =IF(AND(B45>=Assumptions!$C$16,B45<Assumptions!$C$16+Assumptions!$C$18),'Cost Breakdown'!$E$92,0) | F45: =IF(B45=Assumptions!$C$16+Assumptions!$C$18,'Cost Breakdown'!$E$100,0) | G45: =D45+E45+F45 | H45: =IF(AND(B45>=Assumptions!$C$16,B45<Assumptions!$C$16+Assumptions!$C$18),Assumptions!$C$26,0) | I45: =1/(1+Assumptions!$C$21)^C45 | J45: =G45*I45 | K45: =H45*I45
B46: =Assumptions!$C$15+37 | C46: 37 | D46: =IF(B46<Assumptions!$C$16,'Cost Breakdown'!$E$75/Assumptions!$C$17,0) | E46: =IF(AND(B46>=Assumptions!$C$16,B46<Assumptions!$C$16+Assumptions!$C$18),'Cost Breakdown'!$E$92,0) | F46: =IF(B46=Assumptions!$C$16+Assumptions!$C$18,'Cost Breakdown'!$E$100,0) | G46: =D46+E46+F46 | H46: =IF(AND(B46>=Assumptions!$C$16,B46<Assumptions!$C$16+Assumptions!$C$18),Assumptions!$C$26,0) | I46: =1/(1+Assumptions!$C$21)^C46 | J46: =G46*I46 | K46: =H46*I46
B47: =Assumptions!$C$15+38 | C47: 38 | D47: =IF(B47<Assumptions!$C$16,'Cost Breakdown'!$E$75/Assumptions!$C$17,0) | E47: =IF(AND(B47>=Assumptions!$C$16,B47<Assumptions!$C$16+Assumptions!$C$18),'Cost Breakdown'!$E$92,0) | F47: =IF(B47=Assumptions!$C$16+Assumptions!$C$18,'Cost Breakdown'!$E$100,0) | G47: =D47+E47+F47 | H47: =IF(AND(B47>=Assumptions!$C$16,B47<Assumptions!$C$16+Assumptions!$C$18),Assumptions!$C$26,0) | I47: =1/(1+Assumptions!$C$21)^C47 | J47: =G47*I47 | K47: =H47*I47
B48: =Assumptions!$C$15+39 | C48: 39 | D48: =IF(B48<Assumptions!$C$16,'Cost Breakdown'!$E$75/Assumptions!$C$17,0) | E48: =IF(AND(B48>=Assumptions!$C$16,B48<Assumptions!$C$16+Assumptions!$C$18),'Cost Breakdown'!$E$92,0) | F48: =IF(B48=Assumptions!$C$16+Assumptions!$C$18,'Cost Breakdown'!$E$100,0) | G48: =D48+E48+F48 | H48: =IF(AND(B48>=Assumptions!$C$16,B48<Assumptions!$C$16+Assumptions!$C$18),Assumptions!$C$26,0) | I48: =1/(1+Assumptions!$C$21)^C48 | J48: =G48*I48 | K48: =H48*I48
B49: =Assumptions!$C$15+40 | C49: 40 | D49: =IF(B49<Assumptions!$C$16,'Cost Breakdown'!$E$75/Assumptions!$C$17,0) | E49: =IF(AND(B49>=Assumptions!$C$16,B49<Assumptions!$C$16+Assumptions!$C$18),'Cost Breakdown'!$E$92,0) | F49: =IF(B49=Assumptions!$C$16+Assumptions!$C$18,'Cost Breakdown'!$E$100,0) | G49: =D49+E49+F49 | H49: =IF(AND(B49>=Assumptions!$C$16,B49<Assumptions!$C$16+Assumptions!$C$18),Assumptions!$C$26,0) | I49: =1/(1+Assumptions!$C$21)^C49 | J49: =G49*I49 | K49: =H49*I49
B50: =Assumptions!$C$15+41 | C50: 41 | D50: =IF(B50<Assumptions!$C$16,'Cost Breakdown'!$E$75/Assumptions!$C$17,0) | E50: =IF(AND(B50>=Assumptions!$C$16,B50<Assumptions!$C$16+Assumptions!$C$18),'Cost Breakdown'!$E$92,0) | F50: =IF(B50=Assumptions!$C$16+Assumptions!$C$18,'Cost Breakdown'!$E$100,0) | G50: =D50+E50+F50 | H50: =IF(AND(B50>=Assumptions!$C$16,B50<Assumptions!$C$16+Assumptions!$C$18),Assumptions!$C$26,0) | I50: =1/(1+Assumptions!$C$21)^C50 | J50: =G50*I50 | K50: =H50*I50
B51: =Assumptions!$C$15+42 | C51: 42 | D51: =IF(B51<Assumptions!$C$16,'Cost Breakdown'!$E$75/Assumptions!$C$17,0) | E51: =IF(AND(B51>=Assumptions!$C$16,B51<Assumptions!$C$16+Assumptions!$C$18),'Cost Breakdown'!$E$92,0) | F51: =IF(B51=Assumptions!$C$16+Assumptions!$C$18,'Cost Breakdown'!$E$100,0) | G51: =D51+E51+F51 | H51: =IF(AND(B51>=Assumptions!$C$16,B51<Assumptions!$C$16+Assumptions!$C$18),Assumptions!$C$26,0) | I51: =1/(1+Assumptions!$C$21)^C51 | J51: =G51*I51 | K51: =H51*I51
B52: =Assumptions!$C$15+43 | C52: 43 | D52: =IF(B52<Assumptions!$C$16,'Cost Breakdown'!$E$75/Assumptions!$C$17,0) | E52: =IF(AND(B52>=Assumptions!$C$16,B52<Assumptions!$C$16+Assumptions!$C$18),'Cost Breakdown'!$E$92,0) | F52: =IF(B52=Assumptions!$C$16+Assumptions!$C$18,'Cost Breakdown'!$E$100,0) | G52: =D52+E52+F52 | H52: =IF(AND(B52>=Assumptions!$C$16,B52<Assumptions!$C$16+Assumptions!$C$18),Assumptions!$C$26,0) | I52: =1/(1+Assumptions!$C$21)^C52 | J52: =G52*I52 | K52: =H52*I52
B53: =Assumptions!$C$15+44 | C53: 44 | D53: =IF(B53<Assumptions!$C$16,'Cost Breakdown'!$E$75/Assumptions!$C$17,0) | E53: =IF(AND(B53>=Assumptions!$C$16,B53<Assumptions!$C$16+Assumptions!$C$18),'Cost Breakdown'!$E$92,0) | F53: =IF(B53=Assumptions!$C$16+Assumptions!$C$18,'Cost Breakdown'!$E$100,0) | G53: =D53+E53+F53 | H53: =IF(AND(B53>=Assumptions!$C$16,B53<Assumptions!$C$16+Assumptions!$C$18),Assumptions!$C$26,0) | I53: =1/(1+Assumptions!$C$21)^C53 | J53: =G53*I53 | K53: =H53*I53
B54: Totals | D54: =SUM(D9:D53) | E54: =SUM(E9:E53) | F54: =SUM(F9:F53) | G54: =SUM(G9:G53) | H54: =SUM(H9:H53) | J54: =SUM(J9:J53) | K54: =SUM(K9:K53)
